rtl/Full_Adder.v
`timescale 1ns/1ps
//////////////////////////////////////////////////////////////////////////////////
// Company: 
// Engineer: 
// 
// Create Date: 13.11.2023 22:34:34
// Design Name: 
// Module Name: Full_Adder
// Project Name: 
// Target Devices: 
// Tool Versions: 
// Description: A full-adder adds two binary digits A and B and produces the sum (Sum) and the carry-out (Cout).
// 
// Dependencies: 
// 
// Revision:
// Revision 0.01 - File Created
// Additional Comments:
// 
//////////////////////////////////////////////////////////////////////////////////

module Full_Adder(
    input A,
    input B,
    input Cin,
    output Cout,
    output Sum
);

    // Full Adder using dataflow architectural level of abstaction
    assign Cout = (A & B) | ((A ^ B) & Cin);
    assign Sum = A ^ B ^ Cin;

endmodule

testbenches/Full_Adder_tb.v
`timescale 1ns/1ps
`include "Full_Adder.v"

module Full_Adder_tb;

    // input
    reg A;
    reg B;
    reg Cin;
    
    // output
    wire Cout;
    wire Sum;

    // instantiates the unit under test
    Full_Adder uut(A, B, Cin, Cout, Sum);

    // generate stimuli
    initial begin
        $dumpfile("Full_Adder.vcd");
        $dumpvars(0, Full_Adder_tb);

        A = 1'b0;
        B = 1'b0;
        Cin = 1'b0;

        $display("Test complete!");
    end

    always #1 A = A + 1;
    always #2 B = B + 1;
    always #4 Cin = Cin + 1;

    initial $display($time, A, B, Cin, Cout, Sum);

    initial #10 $finish;
    
endmodule

testbenches/Full_Adder.vcd
$date
	Sun Dec 31 23:20:53 2023
$end
$version
	Icarus Verilog
$end
$timescale
	1ps
$end
$scope module Full_Adder_tb $end
$var wire 1 ! Sum $end
$var wire 1 " Cout $end
$var reg 1 # A $end
$var reg 1 $ B $end
$var reg 1 % Cin $end
$scope module uut $end
$var wire 1 # A $end
$var wire 1 $ B $end
$var wire 1 % Cin $end
$var wire 1 " Cout $end
$var wire 1 ! Sum $end
$upscope $end
$upscope $end
$enddefinitions $end
#0
$dumpvars
0%
0$
0#
0"
0!
$end
#1000
1!
1#
#2000
0#
1$
#3000
1"
0!
1#
#4000
0"
1!
0#
0$
1%
#5000
1"
0!
1#
#6000
0#
1$
#7000
1!
1#
#8000
0"
0!
0#
0$
0%
#9000
1!
1#
#10000
0#
1$
